<?xml version="1.0" encoding="utf-8"?>
<world startyear="3000">
	<castles>
		<castle name="Ocean" pos="-85. 56." initial="1" type="0" size="1.1">
			<link castlename="K10" />
			<link castlename="V21" />
			<link castlename="N39" />
		</castle>
		<castle name="B1" pos="-41. -5." initial="0" type="0" size="0.7">
			<link castlename="P15" />
		</castle>
		<castle name="C2" pos="-85. -4." initial="0" type="0" size="0.7">
			<link castlename="Y24" />
			<link castlename="B1" />
		</castle>
		<castle name="D3" pos="-73. 37." initial="0" type="0" size="0.7">
			<link castlename="K10" />
			<link castlename="Ocean" />
		</castle>
		<castle name="E4" pos="-65. -30." initial="0" type="0" size="0.7">
			<link castlename="M12" />
			<link castlename="B1" />
			<link castlename="P42" />
		</castle>
		<castle name="Chronos" pos="-134. -5." initial="1" type="0" size="1.1">
			<link castlename="Q43" />
			<link castlename="Z25" />
			<link castlename="Y24" />
			<link castlename="H33" />
		</castle>
		<castle name="Japet" pos="-80. -72." initial="1" type="0" size="1.2">
			<link castlename="M12" />
		</castle>
		<castle name="K10" pos="-55. 46." initial="0" type="0" size="0.7">
			<link castlename="L38" />
			<link castlename="E30" />
		</castle>
		<castle name="Hyperion" pos="2. -72." initial="1" type="0" size="1.2">
			<link castlename="X23" />
			<link castlename="J35" />
		</castle>
		<castle name="M12" pos="-50. -58." initial="0" type="0" size="0.7">
			<link castlename="P42" />
			<link castlename="B27" />
		</castle>
		<castle name="N13" pos="-21. 23." initial="0" type="0" size="0.7">
			<link castlename="W22" />
			<link castlename="E30" />
			<link castlename="B1" />
		</castle>
		<castle name="Koios" pos="3. 57." initial="1" type="0" size="1.1">
			<link castlename="M39" />
			<link castlename="W22" />
		</castle>
		<castle name="P15" pos="-5. -5." initial="0" type="0" size="0.7">
			<link castlename="D29" />
			<link castlename="C28" />
			<link castlename="N40" />
		</castle>
		<castle name="N14" pos="-22. -34." initial="0" type="0" size="0.7">
			<link castlename="B27" />
			<link castlename="X23" />
			<link castlename="B1" />
		</castle>
		<castle name="Crios" pos="56. -5." initial="1" type="0" size="1.2">
		</castle>
		<castle name="V21" pos="-91. 29." initial="0" type="0" size="0.7">
			<link castlename="D3" />
		</castle>
		<castle name="W22" pos="11. 28." initial="0" type="0" size="0.7">
			<link castlename="D29" />
		</castle>
		<castle name="X23" pos="9. -40." initial="0" type="0" size="0.7">
			<link castlename="C28" />
		</castle>
		<castle name="Y24" pos="-108. -26." initial="0" type="0" size="0.7">
			<link castlename="A26" />
		</castle>
		<castle name="Z25" pos="-106. 15." initial="0" type="0" size="0.7">
			<link castlename="C2" />
			<link castlename="V21" />
			<link castlename="Q43" />
		</castle>
		<castle name="A26" pos="-92. -44." initial="0" type="0" size="0.7">
			<link castlename="E4" />
			<link castlename="Japet" />
		</castle>
		<castle name="B27" pos="-29. -58." initial="0" type="0" size="0.7">
			<link castlename="Hyperion" />
		</castle>
		<castle name="C28" pos="21. -24." initial="0" type="0" size="0.7">
			<link castlename="Crios" />
		</castle>
		<castle name="D29" pos="20. 11." initial="0" type="0" size="0.7">
			<link castlename="Crios" />
		</castle>
		<castle name="E30" pos="-30. 47." initial="0" type="0" size="0.7">
			<link castlename="Koios" />
			<link castlename="M39" />
		</castle>
		<castle name="F31" pos="-129. -46." initial="0" type="0" size="0.7">
		</castle>
		<castle name="G32" pos="-100. -68." initial="0" type="0" size="0.7">
			<link castlename="I34" />
			<link castlename="Japet" />
		</castle>
		<castle name="H33" pos="-131. -27." initial="0" type="0" size="0.7">
			<link castlename="F31" />
		</castle>
		<castle name="I34" pos="-116. -61." initial="0" type="0" size="0.7">
			<link castlename="F31" />
		</castle>
		<castle name="J35" pos="18. -65." initial="0" type="0" size="0.7">
			<link castlename="K36" />
		</castle>
		<castle name="K36" pos="32. -53." initial="0" type="0" size="0.7">
			<link castlename="L37" />
		</castle>
		<castle name="L37" pos="43. -40." initial="0" type="0" size="0.7">
			<link castlename="M38" />
		</castle>
		<castle name="M38" pos="53. -27." initial="0" type="0" size="0.7">
			<link castlename="Crios" />
		</castle>
		<castle name="N39" pos="-68. 60." initial="0" type="0" size="0.7">
			<link castlename="O40" />
		</castle>
		<castle name="O40" pos="-52. 61." initial="0" type="0" size="0.7">
			<link castlename="P41" />
		</castle>
		<castle name="P41" pos="-34. 61." initial="0" type="0" size="0.7">
			<link castlename="Q42" />
		</castle>
		<castle name="Q42" pos="-17. 61." initial="0" type="0" size="0.7">
			<link castlename="Koios" />
		</castle>
		<castle name="L38" pos="-61. 21." initial="0" type="0" size="0.7">
			<link castlename="V21" />
			<link castlename="D3" />
			<link castlename="B1" />
		</castle>
		<castle name="M39" pos="-9. 40." initial="0" type="0" size="0.7">
			<link castlename="N13" />
			<link castlename="W22" />
		</castle>
		<castle name="N40" pos="19. -5." initial="0" type="0" size="0.7">
			<link castlename="Crios" />
			<link castlename="D29" />
			<link castlename="C28" />
		</castle>
		<castle name="O41" pos="-11. -51." initial="0" type="0" size="0.7">
			<link castlename="X23" />
			<link castlename="B27" />
			<link castlename="N14" />
			<link castlename="Hyperion" />
		</castle>
		<castle name="P42" pos="-71. -48." initial="0" type="0" size="0.7">
			<link castlename="A26" />
			<link castlename="Japet" />
		</castle>
		<castle name="Q43" pos="-110. -5." initial="0" type="0" size="0.7">
			<link castlename="C2" />
			<link castlename="Y24" />
		</castle>
	</castles>
</world>